ds_stats_mexico/__init__.py
ds_stats_mexico/functions.py
ds_stats_mexico-1.1.1.dist-info/METADATA
ds_stats_mexico-1.1.1.dist-info/WHEEL
ds_stats_mexico-1.1.1.dist-info/top_level.txt
ds_stats_mexico-1.1.1.dist-info/RECORD
