Metadata-Version: 2.1
Name: ds-stats-mexico
Version: 1.1.1
Summary: Librería de estadística (Gráficas) de México (Paises ricos, envejecimiento, mortalidad infantil)
Home-page: https://github.com/DavichoStar
Author: DavichoStar
Author-email: davichostar@protonmail.com
License: MIT
Requires-Dist: matplotlib
